clipdrop/__init__.py
clipdrop/chunking.py
clipdrop/clipboard.py
clipdrop/detect.py
clipdrop/error_helpers.py
clipdrop/exceptions.py
clipdrop/files.py
clipdrop/html_parser.py
clipdrop/images.py
clipdrop/macos_ai.py
clipdrop/main.py
clipdrop/paranoid.py
clipdrop/pdf.py
clipdrop/subtitles.py
clipdrop/youtube.py
clipdrop/bin/.gitkeep
clipdrop/bin/clipdrop-summarize
clipdrop/bin/clipdrop-transcribe-clipboard
clipdrop-1.6.7.dist-info/METADATA
clipdrop-1.6.7.dist-info/WHEEL
clipdrop-1.6.7.dist-info/entry_points.txt
clipdrop-1.6.7.dist-info/licenses/LICENSE
clipdrop-1.6.7.dist-info/RECORD
