Metadata-Version: 2.4
Name: clipdrop
Version: 1.6.7
Summary: Save clipboard content (text and images) to files with smart format detection
Project-URL: Homepage, https://github.com/prateekjain24/clipdrop
Project-URL: Issues, https://github.com/prateekjain24/clipdrop/issues
Author-email: Prateek <package@prateek.mozmail.com>
License: MIT
License-File: LICENSE
Keywords: cli,clipboard,file-management,image-processing,macos,productivity,text-processing
Classifier: Development Status :: 5 - Production/Stable
Classifier: Environment :: Console
Classifier: Intended Audience :: Developers
Classifier: Intended Audience :: End Users/Desktop
Classifier: License :: OSI Approved :: MIT License
Classifier: Operating System :: MacOS
Classifier: Programming Language :: Python :: 3
Classifier: Programming Language :: Python :: 3.10
Classifier: Programming Language :: Python :: 3.11
Classifier: Programming Language :: Python :: 3.12
Classifier: Programming Language :: Python :: 3.13
Classifier: Topic :: Multimedia :: Graphics :: Capture :: Screen Capture
Classifier: Topic :: Software Development :: Libraries
Classifier: Topic :: System :: Archiving
Classifier: Topic :: Utilities
Requires-Python: >=3.10
Requires-Dist: beautifulsoup4>=4.12.0
Requires-Dist: html2text>=2025.4.15
Requires-Dist: lxml>=5.0.0
Requires-Dist: pillow>=11.3.0
Requires-Dist: pyperclip>=1.9.0
Requires-Dist: reportlab>=4.0.0
Requires-Dist: requests>=2.31.0
Requires-Dist: rich>=14.1.0
Requires-Dist: typer>=0.17.4
Provides-Extra: dev
Requires-Dist: black>=25.1.0; extra == 'dev'
Requires-Dist: mypy>=1.18.1; extra == 'dev'
Requires-Dist: psutil>=5.9.0; extra == 'dev'
Requires-Dist: pytest-cov>=6.0.0; extra == 'dev'
Requires-Dist: pytest>=8.4.2; extra == 'dev'
Requires-Dist: ruff>=0.8.12; extra == 'dev'
Provides-Extra: youtube
Requires-Dist: yt-dlp>=2025.09.05; extra == 'youtube'
